pipeline_staging_properties_pkg/__init__.py
pipeline_staging_properties_pkg/pipeline_staging_properties.py
custom_pipeline_stages_manager-0.1.0.dist-info/LICENSE
custom_pipeline_stages_manager-0.1.0.dist-info/METADATA
custom_pipeline_stages_manager-0.1.0.dist-info/WHEEL
custom_pipeline_stages_manager-0.1.0.dist-info/top_level.txt
custom_pipeline_stages_manager-0.1.0.dist-info/RECORD
