Metadata-Version: 2.1
Name: custom-pipeline-stages-manager
Version: 0.1.0
Summary: A package for managing custom pipeline stages
Home-page: https://github.com/x23203595/PipelineStagingLibrary.git
Author: Vinay Sriram Iyer
Author-email: x23203595@student.ncirl.ie
Classifier: Programming Language :: Python :: 3
Classifier: License :: OSI Approved :: MIT License
Classifier: Operating System :: OS Independent
Requires-Python: >=3.6
License-File: LICENSE
Requires-Dist: boto3
